{"nodes": [{"id": "blog_vibe_coding_12months_log", "label": "Vibe Coding 12 Months: 13+ AI Tools and Prototypes Log", "file_type": "document", "source_file": "src/content/blog/vibe-coding-what-i-built-in-12-months.md", "source_location": null, "source_url": null, "captured_at": null, "author": "Prince Jain", "contributor": null}, {"id": "blog_vibe_coding_methodology", "label": "Vibe Coding Methodology: Clarity First, Phased Builds", "file_type": "document", "source_file": "src/content/blog/vibe-coding-what-i-built-in-12-months.md", "source_location": "line 197", "source_url": null, "captured_at": null, "author": "Prince Jain", "contributor": null}, {"id": "blog_vibe_coding_slap_debug_dashboard", "label": "SLAP Debug Dashboard on Google ADK", "file_type": "document", "source_file": "src/content/blog/vibe-coding-what-i-built-in-12-months.md", "source_location": "line 163", "source_url": null, "captured_at": null, "author": "Prince Jain", "contributor": null}, {"id": "blog_vibe_coding_whispr_flow_offline", "label": "Whispr Flow: Offline Local Whisper Speech-to-Text App", "file_type": "document", "source_file": "src/content/blog/vibe-coding-what-i-built-in-12-months.md", "source_location": "line 83", "source_url": null, "captured_at": null, "author": "Prince Jain", "contributor": null}], "edges": [{"source": "blog_vibe_coding_12months_log", "target": "blog_vibe_coding_methodology", "relation": "references", "confidence": "EXTRACTED", "confidence_score": 1.0, "source_file": "src/content/blog/vibe-coding-what-i-built-in-12-months.md", "source_location": "line 197", "weight": 1.0}, {"source": "blog_vibe_coding_slap_debug_dashboard", "target": "google_adk", "relation": "implements", "confidence": "EXTRACTED", "confidence_score": 1.0, "source_file": "src/content/blog/vibe-coding-what-i-built-in-12-months.md", "source_location": "line 163", "weight": 1.0}, {"source": "blog_vibe_coding_slap_debug_dashboard", "target": "vibe_pm_adk_log_tracer", "relation": "semantically_similar_to", "confidence": "EXTRACTED", "confidence_score": 1.0, "source_file": "src/content/blog/vibe-coding-what-i-built-in-12-months.md", "source_location": "line 163", "weight": 1.0}, {"source": "blog_vibe_coding_whispr_flow_offline", "target": "vibe_pm_whispr_flow", "relation": "semantically_similar_to", "confidence": "EXTRACTED", "confidence_score": 1.0, "source_file": "src/content/blog/vibe-coding-what-i-built-in-12-months.md", "source_location": "line 83", "weight": 1.0}, {"source": "blog_vibe_coding_12months_log", "target": "ai_tools_slap_agentic_commerce", "relation": "references", "confidence": "EXTRACTED", "confidence_score": 1.0, "source_file": "src/content/blog/vibe-coding-what-i-built-in-12-months.md", "source_location": "line 113", "weight": 1.0}], "hyperedges": []}