{"nodes": [{"id": "vibe_coding_whispr", "label": "Vibe Coding WhisprFlow Screenshot", "file_type": "image", "source_file": "public/images/vibe-coding-whispr.png", "source_location": null, "source_url": null, "captured_at": null, "author": null, "contributor": null}], "edges": [{"source": "vibe_coding_whispr", "target": "vibe_coding_slap_debug", "relation": "conceptually_related_to", "confidence": "INFERRED", "confidence_score": 0.8, "source_file": "public/images/vibe-coding-whispr.png", "source_location": null, "weight": 1.0}], "hyperedges": []}